unique_random/__init__.py
unique_random/__main__.py
unique_random/core.py
unique_random/storage.py
unique_random-1.0.0.dist-info/licenses/LICENSE
unique_random-1.0.0.dist-info/METADATA
unique_random-1.0.0.dist-info/WHEEL
unique_random-1.0.0.dist-info/entry_points.txt
unique_random-1.0.0.dist-info/top_level.txt
unique_random-1.0.0.dist-info/RECORD
