Metadata-Version: 2.4
Name: unique_random
Version: 1.0.0
Summary: A Python library for generating unique random numbers with optional persistence and bitmap-based efficiency.
Author-email: Sai Rohith Pasupuleti <sairohithpasupuleti@gmail.com>
License: MIT License
Project-URL: Homepage, https://github.com/sairohithpasupuleti/unique_random
Project-URL: Repository, https://github.com/sairohithpasupuleti/unique_random
Project-URL: Issues, https://github.com/sairohithpasupuleti/unique_random/issues
Keywords: random,unique,numbers,bitmap,generator,persistence,python,deterministic
Classifier: Development Status :: 4 - Beta
Classifier: Intended Audience :: Developers
Classifier: Topic :: Software Development :: Libraries
Classifier: Topic :: Utilities
Classifier: Programming Language :: Python :: 3
Classifier: Programming Language :: Python :: 3.8
Classifier: Programming Language :: Python :: 3.9
Classifier: Programming Language :: Python :: 3.10
Classifier: Programming Language :: Python :: 3.11
Classifier: License :: OSI Approved :: MIT License
Classifier: Operating System :: OS Independent
Requires-Python: >=3.8
License-File: LICENSE
Dynamic: license-file
